README
setup.py
adjointShapeOptimizationFlux/__init__.py
adjointShapeOptimizationFlux.egg-info/PKG-INFO
adjointShapeOptimizationFlux.egg-info/SOURCES.txt
adjointShapeOptimizationFlux.egg-info/dependency_links.txt
adjointShapeOptimizationFlux.egg-info/entry_points.txt
adjointShapeOptimizationFlux.egg-info/requires.txt
adjointShapeOptimizationFlux.egg-info/top_level.txt
adjointShapeOptimizationFlux.egg-info/zip-safe
adjointShapeOptimizationFlux/r2_1_1/__init__.py
adjointShapeOptimizationFlux/r2_1_1/__init__1.py
adjointShapeOptimizationFlux/r2_1_1/adjointOutletPressure/__init__.py
adjointShapeOptimizationFlux/r2_1_1/adjointOutletVelocity/__init__.py